solana_trader_python_proto/__init__.py
solana_trader_python_proto/api.py
solana_trader_python_proto/common.py
solana_trader_python_proto/google/__init__.py
solana_trader_python_proto/google/api.py
solana_trader_python_proto/grpc/__init__.py
solana_trader_python_proto/grpc/gateway/__init__.py
solana_trader_python_proto/grpc/gateway/protoc_gen_openapiv2/__init__.py
solana_trader_python_proto/grpc/gateway/protoc_gen_openapiv2/options.py
solana_trader_python_proto-0.0.7.dist-info/METADATA
solana_trader_python_proto-0.0.7.dist-info/WHEEL
solana_trader_python_proto-0.0.7.dist-info/top_level.txt
solana_trader_python_proto-0.0.7.dist-info/RECORD
