Metadata-Version: 2.1
Name: solana-trader-python-proto
Version: 0.0.7
Summary: proto-generated files for solana-trader-api
